glpi_api/__init__.py
glpi_api/api.py
hitss_glpi-0.1.9.dist-info/METADATA
hitss_glpi-0.1.9.dist-info/WHEEL
hitss_glpi-0.1.9.dist-info/entry_points.txt
hitss_glpi-0.1.9.dist-info/top_level.txt
hitss_glpi-0.1.9.dist-info/RECORD
