Metadata-Version: 2.1
Name: hitss-glpi
Version: 0.1.9
Summary: A Python library to interact with GLPI API
Home-page: https://github.com/De0xyS3
Author: hhportugames
Author-email: my@mundilinux.xyz
License: UNKNOWN
Platform: UNKNOWN
Classifier: Programming Language :: Python :: 3
Classifier: License :: OSI Approved :: MIT License
Classifier: Operating System :: OS Independent
Requires-Python: >=3.6
Requires-Dist: beautifulsoup4
Requires-Dist: requests
Requires-Dist: selenium
Requires-Dist: webdriver-manager
